topsis_nimish_102483077/__init__.py
topsis_nimish_102483077/topsis.py
topsis_nimish_102483077-1.0.2.dist-info/licenses/LICENSE
topsis_nimish_102483077-1.0.2.dist-info/METADATA
topsis_nimish_102483077-1.0.2.dist-info/WHEEL
topsis_nimish_102483077-1.0.2.dist-info/entry_points.txt
topsis_nimish_102483077-1.0.2.dist-info/top_level.txt
topsis_nimish_102483077-1.0.2.dist-info/RECORD
