Metadata-Version: 2.4
Name: Topsis-Nimish-102483077
Version: 1.0.2
Summary: TOPSIS implementation as a Python package
Author: Nimish
License-File: LICENSE
Requires-Dist: pandas
Requires-Dist: numpy
Dynamic: author
Dynamic: description
Dynamic: description-content-type
Dynamic: license-file
Dynamic: requires-dist
Dynamic: summary
